ixora/__init__.py
ixora/__main__.py
ixora/data/graph.html
ixora-0.6.dist-info/METADATA
ixora-0.6.dist-info/WHEEL
ixora-0.6.dist-info/top_level.txt
ixora-0.6.dist-info/RECORD
