Metadata-Version: 2.1
Name: ixora
Version: 0.6
Summary: Automate force-directed graph
Home-page: https://github.com/qeeqbox/ixora
Author: QeeqBox
Author-email: gigaqeeq@gmail.com
License: AGPL-3.0
Platform: UNKNOWN
Requires-Python: >=3
